d2lrecipes/__init__.py
d2lrecipes-0.0.1.dist-info/LICENSE
d2lrecipes-0.0.1.dist-info/LICENSE-SAMPLECODE
d2lrecipes-0.0.1.dist-info/LICENSE-SUMMARY
d2lrecipes-0.0.1.dist-info/METADATA
d2lrecipes-0.0.1.dist-info/WHEEL
d2lrecipes-0.0.1.dist-info/top_level.txt
d2lrecipes-0.0.1.dist-info/zip-safe
d2lrecipes-0.0.1.dist-info/RECORD
