Metadata-Version: 2.1
Name: d2lrecipes
Version: 0.0.1
Summary: D2L Recipes
Home-page: https://recipes.d2l.ai
Author: D2L Developers
Author-email: d2l.devs@gmail.com
License: MIT-0
Platform: UNKNOWN
Requires-Python: >=3.5
Requires-Dist: numpy
Requires-Dist: matplotlib
Requires-Dist: pandas
